{
  "id": "000000",
  "name": "Default Grayscale System",
  "tokens": [
    {
      "name": "0",
      "value": "0rem",
      "category": "spacing",
      "namespace": "spacing",
      "semanticMeaning": "Spacing step 0 in linear scale",
      "mathRelationship": "4 * 0 / 4",
      "scalePosition": 0,
      "generateUtilityClass": true,
      "applicableComponents": ["all"]
    },
    {
      "name": "1",
      "value": "1rem",
      "category": "spacing",
      "namespace": "spacing",
      "semanticMeaning": "Spacing step 1 in linear scale",
      "mathRelationship": "4 * 1 / 4",
      "scalePosition": 1,
      "generateUtilityClass": true,
      "applicableComponents": ["all"]
    },
    {
      "name": "2",
      "value": "2rem",
      "category": "spacing",
      "namespace": "spacing",
      "semanticMeaning": "Spacing step 2 in linear scale",
      "mathRelationship": "4 * 2 / 4",
      "scalePosition": 2,
      "generateUtilityClass": true,
      "applicableComponents": ["all"]
    },
    {
      "name": "3",
      "value": "3rem",
      "category": "spacing",
      "namespace": "spacing",
      "semanticMeaning": "Spacing step 3 in linear scale",
      "mathRelationship": "4 * 3 / 4",
      "scalePosition": 3,
      "generateUtilityClass": true,
      "applicableComponents": ["all"]
    },
    {
      "name": "4",
      "value": "4rem",
      "category": "spacing",
      "namespace": "spacing",
      "semanticMeaning": "Spacing step 4 in linear scale",
      "mathRelationship": "4 * 4 / 4",
      "scalePosition": 4,
      "generateUtilityClass": true,
      "applicableComponents": ["all"]
    },
    {
      "name": "5",
      "value": "5rem",
      "category": "spacing",
      "namespace": "spacing",
      "semanticMeaning": "Spacing step 5 in linear scale",
      "mathRelationship": "4 * 5 / 4",
      "scalePosition": 5,
      "generateUtilityClass": true,
      "applicableComponents": ["all"]
    },
    {
      "name": "6",
      "value": "6rem",
      "category": "spacing",
      "namespace": "spacing",
      "semanticMeaning": "Spacing step 6 in linear scale",
      "mathRelationship": "4 * 6 / 4",
      "scalePosition": 6,
      "generateUtilityClass": true,
      "applicableComponents": ["all"]
    },
    {
      "name": "7",
      "value": "7rem",
      "category": "spacing",
      "namespace": "spacing",
      "semanticMeaning": "Spacing step 7 in linear scale",
      "mathRelationship": "4 * 7 / 4",
      "scalePosition": 7,
      "generateUtilityClass": true,
      "applicableComponents": ["all"]
    },
    {
      "name": "8",
      "value": "8rem",
      "category": "spacing",
      "namespace": "spacing",
      "semanticMeaning": "Spacing step 8 in linear scale",
      "mathRelationship": "4 * 8 / 4",
      "scalePosition": 8,
      "generateUtilityClass": true,
      "applicableComponents": ["all"]
    },
    {
      "name": "9",
      "value": "9rem",
      "category": "spacing",
      "namespace": "spacing",
      "semanticMeaning": "Spacing step 9 in linear scale",
      "mathRelationship": "4 * 9 / 4",
      "scalePosition": 9,
      "generateUtilityClass": true,
      "applicableComponents": ["all"]
    },
    {
      "name": "10",
      "value": "10rem",
      "category": "spacing",
      "namespace": "spacing",
      "semanticMeaning": "Spacing step 10 in linear scale",
      "mathRelationship": "4 * 10 / 4",
      "scalePosition": 10,
      "generateUtilityClass": true,
      "applicableComponents": ["all"]
    },
    {
      "name": "11",
      "value": "11rem",
      "category": "spacing",
      "namespace": "spacing",
      "semanticMeaning": "Spacing step 11 in linear scale",
      "mathRelationship": "4 * 11 / 4",
      "scalePosition": 11,
      "generateUtilityClass": true,
      "applicableComponents": ["all"]
    },
    {
      "name": "12",
      "value": "12rem",
      "category": "spacing",
      "namespace": "spacing",
      "semanticMeaning": "Spacing step 12 in linear scale",
      "mathRelationship": "4 * 12 / 4",
      "scalePosition": 12,
      "generateUtilityClass": true,
      "applicableComponents": ["all"]
    },
    {
      "name": "none",
      "value": "none",
      "category": "shadow",
      "namespace": "shadow",
      "semanticMeaning": "No shadow, flat appearance",
      "scalePosition": 0,
      "generateUtilityClass": true,
      "applicableComponents": ["card", "modal", "dropdown", "tooltip", "popover"]
    },
    {
      "name": "sm",
      "value": "0 1px 2px 0 rgb(0 0 0 / 0.05)",
      "category": "shadow",
      "namespace": "shadow",
      "semanticMeaning": "Subtle depth for cards",
      "scalePosition": 1,
      "generateUtilityClass": true,
      "applicableComponents": ["card", "modal", "dropdown", "tooltip", "popover"]
    },
    {
      "name": "base",
      "value": "0 1px 3px 0 rgb(0 0 0 / 0.1), 0 1px 2px -1px rgb(0 0 0 / 0.1)",
      "category": "shadow",
      "namespace": "shadow",
      "semanticMeaning": "Standard card shadow",
      "scalePosition": 2,
      "generateUtilityClass": true,
      "applicableComponents": ["card", "modal", "dropdown", "tooltip", "popover"]
    },
    {
      "name": "md",
      "value": "0 4px 6px -1px rgb(0 0 0 / 0.1), 0 2px 4px -2px rgb(0 0 0 / 0.1)",
      "category": "shadow",
      "namespace": "shadow",
      "semanticMeaning": "Elevated components",
      "scalePosition": 3,
      "generateUtilityClass": true,
      "applicableComponents": ["card", "modal", "dropdown", "tooltip", "popover"]
    },
    {
      "name": "lg",
      "value": "0 10px 15px -3px rgb(0 0 0 / 0.1), 0 4px 6px -4px rgb(0 0 0 / 0.1)",
      "category": "shadow",
      "namespace": "shadow",
      "semanticMeaning": "Floating elements",
      "scalePosition": 4,
      "generateUtilityClass": true,
      "applicableComponents": ["card", "modal", "dropdown", "tooltip", "popover"]
    },
    {
      "name": "xl",
      "value": "0 20px 25px -5px rgb(0 0 0 / 0.1), 0 8px 10px -6px rgb(0 0 0 / 0.1)",
      "category": "shadow",
      "namespace": "shadow",
      "semanticMeaning": "Modal/dialog shadow",
      "scalePosition": 5,
      "generateUtilityClass": true,
      "applicableComponents": ["card", "modal", "dropdown", "tooltip", "popover"]
    },
    {
      "name": "2xl",
      "value": "0 25px 50px -12px rgb(0 0 0 / 0.25)",
      "category": "shadow",
      "namespace": "shadow",
      "semanticMeaning": "Maximum elevation",
      "scalePosition": 6,
      "generateUtilityClass": true,
      "applicableComponents": ["card", "modal", "dropdown", "tooltip", "popover"]
    },
    {
      "name": "base",
      "value": "0",
      "category": "z-index",
      "namespace": "z",
      "semanticMeaning": "Base content layer",
      "scalePosition": 0,
      "generateUtilityClass": true,
      "applicableComponents": ["overlay"]
    },
    {
      "name": "sticky",
      "value": "10",
      "category": "z-index",
      "namespace": "z",
      "semanticMeaning": "Sticky elements (headers, sidebars)",
      "scalePosition": 1,
      "generateUtilityClass": true,
      "applicableComponents": ["overlay"]
    },
    {
      "name": "dropdown",
      "value": "100",
      "category": "z-index",
      "namespace": "z",
      "semanticMeaning": "Dropdowns and select menus",
      "scalePosition": 2,
      "generateUtilityClass": true,
      "applicableComponents": ["dropdown", "select", "menu"]
    },
    {
      "name": "modal",
      "value": "1000",
      "category": "z-index",
      "namespace": "z",
      "semanticMeaning": "Modal dialogs and overlays",
      "scalePosition": 3,
      "generateUtilityClass": true,
      "applicableComponents": ["modal", "dialog", "sheet"]
    },
    {
      "name": "popover",
      "value": "5000",
      "category": "z-index",
      "namespace": "z",
      "semanticMeaning": "Popovers and tooltips",
      "scalePosition": 4,
      "generateUtilityClass": true,
      "applicableComponents": ["overlay"]
    },
    {
      "name": "notification",
      "value": "10000",
      "category": "z-index",
      "namespace": "z",
      "semanticMeaning": "Toast notifications and alerts",
      "scalePosition": 5,
      "generateUtilityClass": true,
      "applicableComponents": ["toast", "alert", "snackbar"]
    },
    {
      "name": "tooltip",
      "value": "50000",
      "category": "z-index",
      "namespace": "z",
      "semanticMeaning": "Tooltips (highest priority)",
      "scalePosition": 6,
      "generateUtilityClass": true,
      "applicableComponents": ["tooltip", "hint"]
    },
    {
      "name": "max",
      "value": "2147483647",
      "category": "z-index",
      "namespace": "z",
      "semanticMeaning": "Maximum z-index value",
      "scalePosition": 7,
      "generateUtilityClass": true,
      "applicableComponents": ["overlay"]
    },
    {
      "name": "xs",
      "value": "2.5rem",
      "category": "height",
      "namespace": "height",
      "semanticMeaning": "Component height xs for linear scale",
      "mathRelationship": "2.5 + 0",
      "scalePosition": 0,
      "touchTargetSize": 40,
      "generateUtilityClass": true,
      "applicableComponents": ["button", "input", "select", "card"]
    },
    {
      "name": "sm",
      "value": "3rem",
      "category": "height",
      "namespace": "height",
      "semanticMeaning": "Component height sm for linear scale",
      "mathRelationship": "2.5 + 0.5",
      "scalePosition": 1,
      "touchTargetSize": 48,
      "generateUtilityClass": true,
      "applicableComponents": ["button", "input", "select", "card"]
    },
    {
      "name": "md",
      "value": "3.5rem",
      "category": "height",
      "namespace": "height",
      "semanticMeaning": "Component height md for linear scale",
      "mathRelationship": "2.5 + 1",
      "scalePosition": 2,
      "touchTargetSize": 56,
      "generateUtilityClass": true,
      "applicableComponents": ["button", "input", "select", "card"]
    },
    {
      "name": "lg",
      "value": "4rem",
      "category": "height",
      "namespace": "height",
      "semanticMeaning": "Component height lg for linear scale",
      "mathRelationship": "2.5 + 1.5",
      "scalePosition": 3,
      "touchTargetSize": 64,
      "generateUtilityClass": true,
      "applicableComponents": ["button", "input", "select", "card"]
    },
    {
      "name": "xl",
      "value": "4.5rem",
      "category": "height",
      "namespace": "height",
      "semanticMeaning": "Component height xl for linear scale",
      "mathRelationship": "2.5 + 2",
      "scalePosition": 4,
      "touchTargetSize": 72,
      "generateUtilityClass": true,
      "applicableComponents": ["button", "input", "select", "card"]
    },
    {
      "name": "2xl",
      "value": "5rem",
      "category": "height",
      "namespace": "height",
      "semanticMeaning": "Component height 2xl for linear scale",
      "mathRelationship": "2.5 + 2.5",
      "scalePosition": 5,
      "touchTargetSize": 80,
      "generateUtilityClass": true,
      "applicableComponents": ["button", "input", "select", "card"]
    },
    {
      "name": "3xl",
      "value": "5.5rem",
      "category": "height",
      "namespace": "height",
      "semanticMeaning": "Component height 3xl for linear scale",
      "mathRelationship": "2.5 + 3",
      "scalePosition": 6,
      "touchTargetSize": 88,
      "generateUtilityClass": true,
      "applicableComponents": ["button", "input", "select", "card"]
    },
    {
      "name": "4xl",
      "value": "6rem",
      "category": "height",
      "namespace": "height",
      "semanticMeaning": "Component height 4xl for linear scale",
      "mathRelationship": "2.5 + 3.5",
      "scalePosition": 7,
      "touchTargetSize": 96,
      "generateUtilityClass": true,
      "applicableComponents": ["button", "input", "select", "card"]
    },
    {
      "name": "xs",
      "value": "0.382rem",
      "lineHeight": "1.25",
      "category": "font-size",
      "namespace": "font-size",
      "semanticMeaning": "Typography size xs using golden ratio",
      "mathRelationship": "1 * 1.618033988749^-2",
      "scalePosition": 0,
      "generateUtilityClass": true,
      "applicableComponents": ["text", "heading", "label", "button"]
    },
    {
      "name": "xs",
      "value": "1.6",
      "category": "line-height",
      "namespace": "line-height",
      "semanticMeaning": "Line height optimized for xs text",
      "pairedWith": ["xs"],
      "generateUtilityClass": true,
      "applicableComponents": ["text", "heading", "paragraph"]
    },
    {
      "name": "sm",
      "value": "0.618rem",
      "lineHeight": "1.375",
      "category": "font-size",
      "namespace": "font-size",
      "semanticMeaning": "Typography size sm using golden ratio",
      "mathRelationship": "1 * 1.618033988749^-1",
      "scalePosition": 1,
      "generateUtilityClass": true,
      "applicableComponents": ["text", "heading", "label", "button"]
    },
    {
      "name": "sm",
      "value": "1.6",
      "category": "line-height",
      "namespace": "line-height",
      "semanticMeaning": "Line height optimized for sm text",
      "pairedWith": ["sm"],
      "generateUtilityClass": true,
      "applicableComponents": ["text", "heading", "paragraph"]
    },
    {
      "name": "base",
      "value": "1rem",
      "lineHeight": "1.5",
      "category": "font-size",
      "namespace": "font-size",
      "semanticMeaning": "Typography size base using golden ratio",
      "mathRelationship": "1 * 1.618033988749^0",
      "scalePosition": 2,
      "generateUtilityClass": true,
      "applicableComponents": ["text", "heading", "label", "button"]
    },
    {
      "name": "base",
      "value": "1.5",
      "category": "line-height",
      "namespace": "line-height",
      "semanticMeaning": "Line height optimized for base text",
      "pairedWith": ["base"],
      "generateUtilityClass": true,
      "applicableComponents": ["text", "heading", "paragraph"]
    },
    {
      "name": "lg",
      "value": "1.618rem",
      "lineHeight": "1.6",
      "category": "font-size",
      "namespace": "font-size",
      "semanticMeaning": "Typography size lg using golden ratio",
      "mathRelationship": "1 * 1.618033988749^1",
      "scalePosition": 3,
      "generateUtilityClass": true,
      "applicableComponents": ["text", "heading", "label", "button"]
    },
    {
      "name": "lg",
      "value": "1.5",
      "category": "line-height",
      "namespace": "line-height",
      "semanticMeaning": "Line height optimized for lg text",
      "pairedWith": ["lg"],
      "generateUtilityClass": true,
      "applicableComponents": ["text", "heading", "paragraph"]
    },
    {
      "name": "xl",
      "value": "2.618rem",
      "lineHeight": "1.75",
      "category": "font-size",
      "namespace": "font-size",
      "semanticMeaning": "Typography size xl using golden ratio",
      "mathRelationship": "1 * 1.618033988749^2",
      "scalePosition": 4,
      "generateUtilityClass": true,
      "applicableComponents": ["text", "heading", "label", "button"]
    },
    {
      "name": "xl",
      "value": "1.2",
      "category": "line-height",
      "namespace": "line-height",
      "semanticMeaning": "Line height optimized for xl text",
      "pairedWith": ["xl"],
      "generateUtilityClass": true,
      "applicableComponents": ["text", "heading", "paragraph"]
    },
    {
      "name": "2xl",
      "value": "4.236rem",
      "lineHeight": "1.8",
      "category": "font-size",
      "namespace": "font-size",
      "semanticMeaning": "Typography size 2xl using golden ratio",
      "mathRelationship": "1 * 1.618033988749^3",
      "scalePosition": 5,
      "generateUtilityClass": true,
      "applicableComponents": ["text", "heading", "label", "button"]
    },
    {
      "name": "2xl",
      "value": "1.2",
      "category": "line-height",
      "namespace": "line-height",
      "semanticMeaning": "Line height optimized for 2xl text",
      "pairedWith": ["2xl"],
      "generateUtilityClass": true,
      "applicableComponents": ["text", "heading", "paragraph"]
    },
    {
      "name": "3xl",
      "value": "6.854rem",
      "lineHeight": "1.8",
      "category": "font-size",
      "namespace": "font-size",
      "semanticMeaning": "Typography size 3xl using golden ratio",
      "mathRelationship": "1 * 1.618033988749^4",
      "scalePosition": 6,
      "generateUtilityClass": true,
      "applicableComponents": ["text", "heading", "label", "button"]
    },
    {
      "name": "3xl",
      "value": "1.2",
      "category": "line-height",
      "namespace": "line-height",
      "semanticMeaning": "Line height optimized for 3xl text",
      "pairedWith": ["3xl"],
      "generateUtilityClass": true,
      "applicableComponents": ["text", "heading", "paragraph"]
    },
    {
      "name": "4xl",
      "value": "11.09rem",
      "lineHeight": "1.1",
      "category": "font-size",
      "namespace": "font-size",
      "semanticMeaning": "Typography size 4xl using golden ratio",
      "mathRelationship": "1 * 1.618033988749^5",
      "scalePosition": 7,
      "generateUtilityClass": true,
      "applicableComponents": ["text", "heading", "label", "button"]
    },
    {
      "name": "4xl",
      "value": "1.2",
      "category": "line-height",
      "namespace": "line-height",
      "semanticMeaning": "Line height optimized for 4xl text",
      "pairedWith": ["4xl"],
      "generateUtilityClass": true,
      "applicableComponents": ["text", "heading", "paragraph"]
    },
    {
      "name": "5xl",
      "value": "17.944rem",
      "lineHeight": "1.1",
      "category": "font-size",
      "namespace": "font-size",
      "semanticMeaning": "Typography size 5xl using golden ratio",
      "mathRelationship": "1 * 1.618033988749^6",
      "scalePosition": 8,
      "generateUtilityClass": true,
      "applicableComponents": ["text", "heading", "label", "button"]
    },
    {
      "name": "5xl",
      "value": "1.2",
      "category": "line-height",
      "namespace": "line-height",
      "semanticMeaning": "Line height optimized for 5xl text",
      "pairedWith": ["5xl"],
      "generateUtilityClass": true,
      "applicableComponents": ["text", "heading", "paragraph"]
    },
    {
      "name": "6xl",
      "value": "29.034rem",
      "lineHeight": "1.05",
      "category": "font-size",
      "namespace": "font-size",
      "semanticMeaning": "Typography size 6xl using golden ratio",
      "mathRelationship": "1 * 1.618033988749^7",
      "scalePosition": 9,
      "generateUtilityClass": true,
      "applicableComponents": ["text", "heading", "label", "button"]
    },
    {
      "name": "6xl",
      "value": "1.2",
      "category": "line-height",
      "namespace": "line-height",
      "semanticMeaning": "Line height optimized for 6xl text",
      "pairedWith": ["6xl"],
      "generateUtilityClass": true,
      "applicableComponents": ["text", "heading", "paragraph"]
    },
    {
      "name": "7xl",
      "value": "46.979rem",
      "lineHeight": "1.05",
      "category": "font-size",
      "namespace": "font-size",
      "semanticMeaning": "Typography size 7xl using golden ratio",
      "mathRelationship": "1 * 1.618033988749^8",
      "scalePosition": 10,
      "generateUtilityClass": true,
      "applicableComponents": ["text", "heading", "label", "button"]
    },
    {
      "name": "7xl",
      "value": "1.2",
      "category": "line-height",
      "namespace": "line-height",
      "semanticMeaning": "Line height optimized for 7xl text",
      "pairedWith": ["7xl"],
      "generateUtilityClass": true,
      "applicableComponents": ["text", "heading", "paragraph"]
    },
    {
      "name": "8xl",
      "value": "76.013rem",
      "lineHeight": "1",
      "category": "font-size",
      "namespace": "font-size",
      "semanticMeaning": "Typography size 8xl using golden ratio",
      "mathRelationship": "1 * 1.618033988749^9",
      "scalePosition": 11,
      "generateUtilityClass": true,
      "applicableComponents": ["text", "heading", "label", "button"]
    },
    {
      "name": "8xl",
      "value": "1.2",
      "category": "line-height",
      "namespace": "line-height",
      "semanticMeaning": "Line height optimized for 8xl text",
      "pairedWith": ["8xl"],
      "generateUtilityClass": true,
      "applicableComponents": ["text", "heading", "paragraph"]
    },
    {
      "name": "9xl",
      "value": "122.992rem",
      "lineHeight": "1",
      "category": "font-size",
      "namespace": "font-size",
      "semanticMeaning": "Typography size 9xl using golden ratio",
      "mathRelationship": "1 * 1.618033988749^10",
      "scalePosition": 12,
      "generateUtilityClass": true,
      "applicableComponents": ["text", "heading", "label", "button"]
    },
    {
      "name": "9xl",
      "value": "1.2",
      "category": "line-height",
      "namespace": "line-height",
      "semanticMeaning": "Line height optimized for 9xl text",
      "pairedWith": ["9xl"],
      "generateUtilityClass": true,
      "applicableComponents": ["text", "heading", "paragraph"]
    },
    {
      "name": "primary",
      "value": "oklch(0.45 0.12 240)",
      "darkValue": "oklch(0.8 0.05 240)",
      "category": "color",
      "namespace": "color",
      "semanticMeaning": "Primary brand color for main actions",
      "scalePosition": 0,
      "generateUtilityClass": true,
      "applicableComponents": ["button", "link", "badge"],
      "trustLevel": "high",
      "cognitiveLoad": 4
    },
    {
      "name": "primary-foreground",
      "value": "oklch(0.98 0.002 240)",
      "darkValue": "oklch(0.1 0 0)",
      "category": "color",
      "namespace": "color",
      "semanticMeaning": "Text on primary background",
      "scalePosition": 1,
      "generateUtilityClass": true,
      "applicableComponents": ["button", "link", "badge"],
      "trustLevel": "high",
      "cognitiveLoad": 4
    },
    {
      "name": "secondary",
      "value": "oklch(0.35 0.08 240)",
      "darkValue": "oklch(0.15 0 0)",
      "category": "color",
      "namespace": "color",
      "semanticMeaning": "Secondary actions and elements",
      "scalePosition": 2,
      "generateUtilityClass": true,
      "applicableComponents": ["all"],
      "trustLevel": "low",
      "cognitiveLoad": 2
    },
    {
      "name": "secondary-foreground",
      "value": "oklch(0.95 0.005 240)",
      "darkValue": "oklch(0.9 0 0)",
      "category": "color",
      "namespace": "color",
      "semanticMeaning": "Text on secondary background",
      "scalePosition": 3,
      "generateUtilityClass": true,
      "applicableComponents": ["all"],
      "trustLevel": "low",
      "cognitiveLoad": 2
    },
    {
      "name": "accent",
      "value": "oklch(0.45 0.1 270)",
      "darkValue": "oklch(0.7 0.08 270)",
      "category": "color",
      "namespace": "color",
      "semanticMeaning": "Accent color for highlights",
      "scalePosition": 4,
      "generateUtilityClass": true,
      "applicableComponents": ["all"],
      "trustLevel": "low",
      "cognitiveLoad": 2
    },
    {
      "name": "accent-foreground",
      "value": "oklch(0.98 0.002 270)",
      "darkValue": "oklch(0.1 0 0)",
      "category": "color",
      "namespace": "color",
      "semanticMeaning": "Text on accent background",
      "scalePosition": 5,
      "generateUtilityClass": true,
      "applicableComponents": ["all"],
      "trustLevel": "low",
      "cognitiveLoad": 2
    },
    {
      "name": "info",
      "value": "oklch(0.45 0.1 210)",
      "darkValue": "oklch(0.7 0.08 210)",
      "category": "color",
      "namespace": "color",
      "semanticMeaning": "Informational states and messages",
      "scalePosition": 6,
      "generateUtilityClass": true,
      "applicableComponents": ["all"],
      "trustLevel": "low",
      "cognitiveLoad": 2
    },
    {
      "name": "info-foreground",
      "value": "oklch(0.98 0.002 210)",
      "darkValue": "oklch(0.1 0 0)",
      "category": "color",
      "namespace": "color",
      "semanticMeaning": "Text on info background",
      "scalePosition": 7,
      "generateUtilityClass": true,
      "applicableComponents": ["all"],
      "trustLevel": "low",
      "cognitiveLoad": 2
    },
    {
      "name": "success",
      "value": "oklch(0.45 0.1 150)",
      "darkValue": "oklch(0.7 0.08 150)",
      "category": "color",
      "namespace": "color",
      "semanticMeaning": "Success states and confirmations",
      "scalePosition": 8,
      "generateUtilityClass": true,
      "applicableComponents": ["button", "alert", "badge", "icon"],
      "trustLevel": "low",
      "cognitiveLoad": 2
    },
    {
      "name": "success-foreground",
      "value": "oklch(0.98 0.002 150)",
      "darkValue": "oklch(0.1 0 0)",
      "category": "color",
      "namespace": "color",
      "semanticMeaning": "Text on success background",
      "scalePosition": 9,
      "generateUtilityClass": true,
      "applicableComponents": ["button", "alert", "badge", "icon"],
      "trustLevel": "low",
      "cognitiveLoad": 2
    },
    {
      "name": "warning",
      "value": "oklch(0.55 0.12 60)",
      "darkValue": "oklch(0.65 0.1 60)",
      "category": "color",
      "namespace": "color",
      "semanticMeaning": "Warning states and cautions",
      "scalePosition": 10,
      "generateUtilityClass": true,
      "applicableComponents": ["all"],
      "trustLevel": "medium",
      "cognitiveLoad": 6
    },
    {
      "name": "warning-foreground",
      "value": "oklch(0.15 0.02 60)",
      "darkValue": "oklch(0.1 0 0)",
      "category": "color",
      "namespace": "color",
      "semanticMeaning": "Text on warning background",
      "scalePosition": 11,
      "generateUtilityClass": true,
      "applicableComponents": ["all"],
      "trustLevel": "medium",
      "cognitiveLoad": 6
    },
    {
      "name": "destructive",
      "value": "oklch(0.4 0.15 20)",
      "darkValue": "oklch(0.5 0.2 20)",
      "category": "color",
      "namespace": "color",
      "semanticMeaning": "Destructive actions and errors",
      "scalePosition": 12,
      "generateUtilityClass": true,
      "applicableComponents": ["button", "alert", "badge"],
      "trustLevel": "critical",
      "cognitiveLoad": 8
    },
    {
      "name": "destructive-foreground",
      "value": "oklch(0.98 0.002 20)",
      "darkValue": "oklch(0.98 0.002 20)",
      "category": "color",
      "namespace": "color",
      "semanticMeaning": "Text on destructive background",
      "scalePosition": 13,
      "generateUtilityClass": true,
      "applicableComponents": ["button", "alert", "badge"],
      "trustLevel": "critical",
      "cognitiveLoad": 8
    },
    {
      "name": "highlight",
      "value": "oklch(0.55 0.15 90)",
      "darkValue": "oklch(0.6 0.12 90)",
      "category": "color",
      "namespace": "color",
      "semanticMeaning": "Text highlighting and selection",
      "scalePosition": 14,
      "generateUtilityClass": true,
      "applicableComponents": ["all"],
      "trustLevel": "low",
      "cognitiveLoad": 2
    },
    {
      "name": "highlight-foreground",
      "value": "oklch(0.15 0.02 90)",
      "darkValue": "oklch(0.1 0 0)",
      "category": "color",
      "namespace": "color",
      "semanticMeaning": "Text on highlight background",
      "scalePosition": 15,
      "generateUtilityClass": true,
      "applicableComponents": ["all"],
      "trustLevel": "low",
      "cognitiveLoad": 2
    },
    {
      "name": "background",
      "value": "oklch(1 0 0)",
      "darkValue": "oklch(0.09 0 0)",
      "category": "color",
      "namespace": "color",
      "semanticMeaning": "Main background color",
      "scalePosition": 16,
      "generateUtilityClass": true,
      "applicableComponents": ["body", "card", "modal"],
      "trustLevel": "low",
      "cognitiveLoad": 2
    },
    {
      "name": "foreground",
      "value": "oklch(0.15 0.005 240)",
      "darkValue": "oklch(0.95 0 0)",
      "category": "color",
      "namespace": "color",
      "semanticMeaning": "Main text color",
      "scalePosition": 17,
      "generateUtilityClass": true,
      "applicableComponents": ["all"],
      "trustLevel": "low",
      "cognitiveLoad": 2
    },
    {
      "name": "muted",
      "value": "oklch(0.96 0.005 240)",
      "darkValue": "oklch(0.15 0 0)",
      "category": "color",
      "namespace": "color",
      "semanticMeaning": "Muted background for secondary content",
      "scalePosition": 18,
      "generateUtilityClass": true,
      "applicableComponents": ["all"],
      "trustLevel": "low",
      "cognitiveLoad": 2
    },
    {
      "name": "muted-foreground",
      "value": "oklch(0.45 0.02 240)",
      "darkValue": "oklch(0.65 0 0)",
      "category": "color",
      "namespace": "color",
      "semanticMeaning": "Muted text color",
      "scalePosition": 19,
      "generateUtilityClass": true,
      "applicableComponents": ["all"],
      "trustLevel": "low",
      "cognitiveLoad": 2
    },
    {
      "name": "border",
      "value": "oklch(0.88 0.02 240)",
      "darkValue": "oklch(0.27 0 0)",
      "category": "color",
      "namespace": "color",
      "semanticMeaning": "Border color for components",
      "scalePosition": 20,
      "generateUtilityClass": true,
      "applicableComponents": ["all"],
      "trustLevel": "low",
      "cognitiveLoad": 2
    },
    {
      "name": "input",
      "value": "oklch(0.88 0.02 240)",
      "darkValue": "oklch(0.27 0 0)",
      "category": "color",
      "namespace": "color",
      "semanticMeaning": "Input field borders",
      "scalePosition": 21,
      "generateUtilityClass": true,
      "applicableComponents": ["all"],
      "trustLevel": "low",
      "cognitiveLoad": 2
    },
    {
      "name": "ring",
      "value": "oklch(0.45 0.12 240)",
      "darkValue": "oklch(0.8 0.05 240)",
      "category": "color",
      "namespace": "color",
      "semanticMeaning": "Focus ring color",
      "scalePosition": 22,
      "generateUtilityClass": true,
      "applicableComponents": ["all"],
      "trustLevel": "low",
      "cognitiveLoad": 2
    },
    {
      "name": "card",
      "value": "oklch(1 0 0)",
      "darkValue": "oklch(0.09 0 0)",
      "category": "color",
      "namespace": "color",
      "semanticMeaning": "Card background color",
      "scalePosition": 23,
      "generateUtilityClass": true,
      "applicableComponents": ["card"],
      "trustLevel": "low",
      "cognitiveLoad": 2
    },
    {
      "name": "card-foreground",
      "value": "oklch(0.15 0.005 240)",
      "darkValue": "oklch(0.95 0 0)",
      "category": "color",
      "namespace": "color",
      "semanticMeaning": "Text on card background",
      "scalePosition": 24,
      "generateUtilityClass": true,
      "applicableComponents": ["card"],
      "trustLevel": "low",
      "cognitiveLoad": 2
    },
    {
      "name": "popover",
      "value": "oklch(1 0 0)",
      "darkValue": "oklch(0.09 0 0)",
      "category": "color",
      "namespace": "color",
      "semanticMeaning": "Popover background color",
      "scalePosition": 25,
      "generateUtilityClass": true,
      "applicableComponents": ["popover", "tooltip", "dropdown"],
      "trustLevel": "low",
      "cognitiveLoad": 2
    },
    {
      "name": "popover-foreground",
      "value": "oklch(0.15 0.005 240)",
      "darkValue": "oklch(0.95 0 0)",
      "category": "color",
      "namespace": "color",
      "semanticMeaning": "Text on popover background",
      "scalePosition": 26,
      "generateUtilityClass": true,
      "applicableComponents": ["popover", "tooltip", "dropdown"],
      "trustLevel": "low",
      "cognitiveLoad": 2
    },
    {
      "name": "instant",
      "value": "75ms",
      "category": "motion",
      "namespace": "duration",
      "semanticMeaning": "Instant feedback for immediate response",
      "scalePosition": 0,
      "cognitiveLoad": 1,
      "reducedMotionAware": true,
      "motionDuration": 75,
      "generateUtilityClass": true,
      "applicableComponents": ["all"]
    },
    {
      "name": "fast",
      "value": "150ms",
      "category": "motion",
      "namespace": "duration",
      "semanticMeaning": "Fast animations for interactive elements",
      "scalePosition": 1,
      "cognitiveLoad": 2,
      "reducedMotionAware": true,
      "motionDuration": 150,
      "generateUtilityClass": true,
      "applicableComponents": ["all"]
    },
    {
      "name": "standard",
      "value": "300ms",
      "category": "motion",
      "namespace": "duration",
      "semanticMeaning": "Standard duration for most transitions",
      "scalePosition": 2,
      "cognitiveLoad": 3,
      "reducedMotionAware": true,
      "motionDuration": 300,
      "generateUtilityClass": true,
      "applicableComponents": ["all"]
    },
    {
      "name": "deliberate",
      "value": "500ms",
      "category": "motion",
      "namespace": "duration",
      "semanticMeaning": "Deliberate timing for important changes",
      "scalePosition": 3,
      "cognitiveLoad": 5,
      "reducedMotionAware": true,
      "motionDuration": 500,
      "generateUtilityClass": true,
      "applicableComponents": ["all"]
    },
    {
      "name": "slow",
      "value": "700ms",
      "category": "motion",
      "namespace": "duration",
      "semanticMeaning": "Slow transitions for large changes",
      "scalePosition": 4,
      "cognitiveLoad": 7,
      "reducedMotionAware": true,
      "motionDuration": 700,
      "generateUtilityClass": true,
      "applicableComponents": ["all"]
    },
    {
      "name": "dramatic",
      "value": "1000ms",
      "category": "motion",
      "namespace": "duration",
      "semanticMeaning": "Dramatic timing for emphasis",
      "scalePosition": 5,
      "cognitiveLoad": 9,
      "reducedMotionAware": true,
      "motionDuration": 1000,
      "generateUtilityClass": true,
      "applicableComponents": ["all"]
    },
    {
      "name": "linear",
      "value": "linear",
      "category": "easing",
      "namespace": "ease",
      "semanticMeaning": "Linear timing for mechanical movement",
      "scalePosition": 0,
      "generateUtilityClass": true,
      "applicableComponents": ["all"]
    },
    {
      "name": "smooth",
      "value": "ease-in-out",
      "category": "easing",
      "namespace": "ease",
      "semanticMeaning": "Smooth natural movement",
      "scalePosition": 1,
      "generateUtilityClass": true,
      "applicableComponents": ["all"]
    },
    {
      "name": "accelerating",
      "value": "ease-out",
      "category": "easing",
      "namespace": "ease",
      "semanticMeaning": "Welcoming entrance animation",
      "scalePosition": 2,
      "generateUtilityClass": true,
      "applicableComponents": ["all"]
    },
    {
      "name": "decelerating",
      "value": "ease-in",
      "category": "easing",
      "namespace": "ease",
      "semanticMeaning": "Graceful exit animation",
      "scalePosition": 3,
      "generateUtilityClass": true,
      "applicableComponents": ["all"]
    },
    {
      "name": "bouncy",
      "value": "cubic-bezier(0.175, 0.885, 0.32, 1.275)",
      "category": "easing",
      "namespace": "ease",
      "semanticMeaning": "Playful bounce for celebrations",
      "scalePosition": 4,
      "generateUtilityClass": true,
      "applicableComponents": ["all"]
    },
    {
      "name": "snappy",
      "value": "cubic-bezier(0.25, 0.46, 0.45, 0.94)",
      "category": "easing",
      "namespace": "ease",
      "semanticMeaning": "Sharp responsive feedback",
      "scalePosition": 5,
      "generateUtilityClass": true,
      "applicableComponents": ["all"]
    },
    {
      "name": "none",
      "value": "0",
      "category": "border-radius",
      "namespace": "radius",
      "semanticMeaning": "No border radius, sharp corners",
      "scalePosition": 0,
      "generateUtilityClass": true,
      "applicableComponents": ["button", "input", "card", "modal", "badge", "avatar"]
    },
    {
      "name": "sm",
      "value": "0.125rem",
      "category": "border-radius",
      "namespace": "radius",
      "semanticMeaning": "Small radius for subtle rounding",
      "scalePosition": 1,
      "generateUtilityClass": true,
      "applicableComponents": ["button", "input", "card", "modal", "badge", "avatar"]
    },
    {
      "name": "base",
      "value": "0.25rem",
      "category": "border-radius",
      "namespace": "radius",
      "semanticMeaning": "Default radius for most components",
      "scalePosition": 2,
      "generateUtilityClass": true,
      "applicableComponents": ["button", "input", "card", "modal", "badge", "avatar"]
    },
    {
      "name": "md",
      "value": "0.375rem",
      "category": "border-radius",
      "namespace": "radius",
      "semanticMeaning": "Medium radius for cards and panels",
      "scalePosition": 3,
      "generateUtilityClass": true,
      "applicableComponents": ["button", "input", "card", "modal", "badge", "avatar"]
    },
    {
      "name": "lg",
      "value": "0.5rem",
      "category": "border-radius",
      "namespace": "radius",
      "semanticMeaning": "Large radius for prominent elements",
      "scalePosition": 4,
      "generateUtilityClass": true,
      "applicableComponents": ["button", "input", "card", "modal", "badge", "avatar"]
    },
    {
      "name": "xl",
      "value": "0.75rem",
      "category": "border-radius",
      "namespace": "radius",
      "semanticMeaning": "Extra large radius for hero elements",
      "scalePosition": 5,
      "generateUtilityClass": true,
      "applicableComponents": ["button", "input", "card", "modal", "badge", "avatar"]
    },
    {
      "name": "2xl",
      "value": "1rem",
      "category": "border-radius",
      "namespace": "radius",
      "semanticMeaning": "Maximum standard radius",
      "scalePosition": 6,
      "generateUtilityClass": true,
      "applicableComponents": ["button", "input", "card", "modal", "badge", "avatar"]
    },
    {
      "name": "3xl",
      "value": "1.5rem",
      "category": "border-radius",
      "namespace": "radius",
      "semanticMeaning": "Very large radius for special cases",
      "scalePosition": 7,
      "generateUtilityClass": true,
      "applicableComponents": ["button", "input", "card", "modal", "badge", "avatar"]
    },
    {
      "name": "full",
      "value": "9999px",
      "category": "border-radius",
      "namespace": "radius",
      "semanticMeaning": "Fully rounded (pills, avatars)",
      "scalePosition": 8,
      "generateUtilityClass": true,
      "applicableComponents": ["button", "input", "card", "modal", "badge", "avatar"]
    },
    {
      "name": "min",
      "value": "44px",
      "category": "touch-target",
      "namespace": "touch",
      "semanticMeaning": "WCAG AAA minimum touch target",
      "scalePosition": 0,
      "touchTargetSize": 44,
      "accessibilityLevel": "AAA",
      "generateUtilityClass": true,
      "applicableComponents": ["button", "link", "interactive", "icon-button"]
    },
    {
      "name": "comfortable",
      "value": "48px",
      "category": "touch-target",
      "namespace": "touch",
      "semanticMeaning": "Comfortable touch target",
      "scalePosition": 1,
      "touchTargetSize": 48,
      "accessibilityLevel": "AA",
      "generateUtilityClass": true,
      "applicableComponents": ["button", "link", "interactive", "icon-button"]
    },
    {
      "name": "generous",
      "value": "56px",
      "category": "touch-target",
      "namespace": "touch",
      "semanticMeaning": "Generous touch target for accessibility",
      "scalePosition": 2,
      "touchTargetSize": 56,
      "accessibilityLevel": "AA",
      "generateUtilityClass": true,
      "applicableComponents": ["button", "link", "interactive", "icon-button"]
    },
    {
      "name": "large",
      "value": "64px",
      "category": "touch-target",
      "namespace": "touch",
      "semanticMeaning": "Large touch target for primary actions",
      "scalePosition": 3,
      "touchTargetSize": 64,
      "accessibilityLevel": "AA",
      "generateUtilityClass": true,
      "applicableComponents": ["button", "link", "interactive", "icon-button"]
    },
    {
      "name": "disabled",
      "value": "0.5",
      "category": "opacity",
      "namespace": "opacity",
      "semanticMeaning": "Disabled state opacity",
      "scalePosition": 0,
      "generateUtilityClass": true,
      "applicableComponents": ["button", "input", "text"],
      "interactionType": "disabled"
    },
    {
      "name": "loading",
      "value": "0.7",
      "category": "opacity",
      "namespace": "opacity",
      "semanticMeaning": "Loading state opacity",
      "scalePosition": 1,
      "generateUtilityClass": true,
      "applicableComponents": ["all"],
      "interactionType": "loading"
    },
    {
      "name": "overlay",
      "value": "0.8",
      "category": "opacity",
      "namespace": "opacity",
      "semanticMeaning": "Modal overlay background",
      "scalePosition": 2,
      "generateUtilityClass": true,
      "applicableComponents": ["modal", "dialog"]
    },
    {
      "name": "backdrop",
      "value": "0.25",
      "category": "opacity",
      "namespace": "opacity",
      "semanticMeaning": "Subtle backdrop opacity",
      "scalePosition": 3,
      "generateUtilityClass": true,
      "applicableComponents": ["all"]
    },
    {
      "name": "hover",
      "value": "0.9",
      "category": "opacity",
      "namespace": "opacity",
      "semanticMeaning": "Hover state opacity",
      "scalePosition": 4,
      "generateUtilityClass": true,
      "applicableComponents": ["all"],
      "interactionType": "hover"
    },
    {
      "name": "focus",
      "value": "1",
      "category": "opacity",
      "namespace": "opacity",
      "semanticMeaning": "Focus state (full opacity)",
      "scalePosition": 5,
      "generateUtilityClass": true,
      "applicableComponents": ["all"],
      "interactionType": "focus"
    },
    {
      "name": "sans",
      "value": "\"Inter\", system-ui, sans-serif",
      "category": "font-family",
      "namespace": "font",
      "semanticMeaning": "Primary sans-serif for UI and body text",
      "scalePosition": 0,
      "generateUtilityClass": true,
      "applicableComponents": ["all"]
    },
    {
      "name": "serif",
      "value": "\"Crimson Text\", Georgia, serif",
      "category": "font-family",
      "namespace": "font",
      "semanticMeaning": "Serif font for editorial content",
      "scalePosition": 1,
      "generateUtilityClass": true,
      "applicableComponents": ["article", "blog"]
    },
    {
      "name": "mono",
      "value": "\"JetBrains Mono\", \"Fira Code\", monospace",
      "category": "font-family",
      "namespace": "font",
      "semanticMeaning": "Monospace font for code and data",
      "scalePosition": 2,
      "generateUtilityClass": true,
      "applicableComponents": ["code", "pre", "kbd"]
    },
    {
      "name": "display",
      "value": "\"Inter Display\", system-ui, sans-serif",
      "category": "font-family",
      "namespace": "font",
      "semanticMeaning": "Display font for headings and marketing",
      "scalePosition": 3,
      "generateUtilityClass": true,
      "applicableComponents": ["h1", "h2", "hero"]
    },
    {
      "name": "thin",
      "value": "100",
      "category": "font-weight",
      "namespace": "font-weight",
      "semanticMeaning": "Thin weight for delicate text",
      "scalePosition": 0,
      "generateUtilityClass": true,
      "applicableComponents": ["text"]
    },
    {
      "name": "extralight",
      "value": "200",
      "category": "font-weight",
      "namespace": "font-weight",
      "semanticMeaning": "Extra light weight",
      "scalePosition": 1,
      "generateUtilityClass": true,
      "applicableComponents": ["text"]
    },
    {
      "name": "light",
      "value": "300",
      "category": "font-weight",
      "namespace": "font-weight",
      "semanticMeaning": "Light weight for subtle text",
      "scalePosition": 2,
      "generateUtilityClass": true,
      "applicableComponents": ["text"]
    },
    {
      "name": "normal",
      "value": "400",
      "category": "font-weight",
      "namespace": "font-weight",
      "semanticMeaning": "Normal weight for body text",
      "scalePosition": 3,
      "generateUtilityClass": true,
      "applicableComponents": ["p", "span", "body"]
    },
    {
      "name": "medium",
      "value": "500",
      "category": "font-weight",
      "namespace": "font-weight",
      "semanticMeaning": "Medium weight for emphasis",
      "scalePosition": 4,
      "generateUtilityClass": true,
      "applicableComponents": ["text"]
    },
    {
      "name": "semibold",
      "value": "600",
      "category": "font-weight",
      "namespace": "font-weight",
      "semanticMeaning": "Semi-bold for subheadings",
      "scalePosition": 5,
      "generateUtilityClass": true,
      "applicableComponents": ["text"]
    },
    {
      "name": "bold",
      "value": "700",
      "category": "font-weight",
      "namespace": "font-weight",
      "semanticMeaning": "Bold for headings and emphasis",
      "scalePosition": 6,
      "generateUtilityClass": true,
      "applicableComponents": ["h1", "h2", "h3", "strong"]
    },
    {
      "name": "extrabold",
      "value": "800",
      "category": "font-weight",
      "namespace": "font-weight",
      "semanticMeaning": "Extra bold for strong emphasis",
      "scalePosition": 7,
      "generateUtilityClass": true,
      "applicableComponents": ["text"]
    },
    {
      "name": "black",
      "value": "900",
      "category": "font-weight",
      "namespace": "font-weight",
      "semanticMeaning": "Black weight for maximum impact",
      "scalePosition": 8,
      "generateUtilityClass": true,
      "applicableComponents": ["text"]
    },
    {
      "name": "tighter",
      "value": "-0.05em",
      "category": "letter-spacing",
      "namespace": "tracking",
      "semanticMeaning": "Tighter letter spacing for large text",
      "scalePosition": 0,
      "generateUtilityClass": true,
      "applicableComponents": ["body", "caption"]
    },
    {
      "name": "tight",
      "value": "-0.025em",
      "category": "letter-spacing",
      "namespace": "tracking",
      "semanticMeaning": "Slightly tighter spacing",
      "scalePosition": 1,
      "generateUtilityClass": true,
      "applicableComponents": ["body", "caption"]
    },
    {
      "name": "normal",
      "value": "0em",
      "category": "letter-spacing",
      "namespace": "tracking",
      "semanticMeaning": "Normal letter spacing",
      "scalePosition": 2,
      "generateUtilityClass": true,
      "applicableComponents": ["text"]
    },
    {
      "name": "wide",
      "value": "0.025em",
      "category": "letter-spacing",
      "namespace": "tracking",
      "semanticMeaning": "Wider spacing for readability",
      "scalePosition": 3,
      "generateUtilityClass": true,
      "applicableComponents": ["h1", "h2", "display"]
    },
    {
      "name": "wider",
      "value": "0.05em",
      "category": "letter-spacing",
      "namespace": "tracking",
      "semanticMeaning": "Wide spacing for emphasis",
      "scalePosition": 4,
      "generateUtilityClass": true,
      "applicableComponents": ["h1", "h2", "display"]
    },
    {
      "name": "widest",
      "value": "0.1em",
      "category": "letter-spacing",
      "namespace": "tracking",
      "semanticMeaning": "Maximum spacing for display text",
      "scalePosition": 5,
      "generateUtilityClass": true,
      "applicableComponents": ["h1", "h2", "display"]
    },
    {
      "name": "xs",
      "value": "320px",
      "category": "breakpoint",
      "namespace": "screen",
      "semanticMeaning": "Extra small mobile devices",
      "scalePosition": 0,
      "generateUtilityClass": false,
      "applicableComponents": ["layout", "grid", "responsive"],
      "viewportAware": true
    },
    {
      "name": "sm",
      "value": "640px",
      "category": "breakpoint",
      "namespace": "screen",
      "semanticMeaning": "Small tablets and large phones",
      "scalePosition": 1,
      "generateUtilityClass": false,
      "applicableComponents": ["layout", "grid", "responsive"],
      "viewportAware": true
    },
    {
      "name": "md",
      "value": "768px",
      "category": "breakpoint",
      "namespace": "screen",
      "semanticMeaning": "Medium tablets",
      "scalePosition": 2,
      "generateUtilityClass": false,
      "applicableComponents": ["layout", "grid", "responsive"],
      "viewportAware": true
    },
    {
      "name": "lg",
      "value": "1024px",
      "category": "breakpoint",
      "namespace": "screen",
      "semanticMeaning": "Large tablets and small laptops",
      "scalePosition": 3,
      "generateUtilityClass": false,
      "applicableComponents": ["layout", "grid", "responsive"],
      "viewportAware": true
    },
    {
      "name": "xl",
      "value": "1280px",
      "category": "breakpoint",
      "namespace": "screen",
      "semanticMeaning": "Large laptops and desktops",
      "scalePosition": 4,
      "generateUtilityClass": false,
      "applicableComponents": ["layout", "grid", "responsive"],
      "viewportAware": true
    },
    {
      "name": "2xl",
      "value": "1536px",
      "category": "breakpoint",
      "namespace": "screen",
      "semanticMeaning": "Large desktops and ultrawide",
      "scalePosition": 5,
      "generateUtilityClass": false,
      "applicableComponents": ["layout", "grid", "responsive"],
      "viewportAware": true
    },
    {
      "name": "xs",
      "value": "20rem",
      "category": "container",
      "namespace": "container",
      "semanticMeaning": "Extra small container (320px)",
      "scalePosition": 0,
      "generateUtilityClass": true,
      "applicableComponents": ["layout", "wrapper", "max-width"],
      "containerQueryAware": true
    },
    {
      "name": "sm",
      "value": "24rem",
      "category": "container",
      "namespace": "container",
      "semanticMeaning": "Small container (384px)",
      "scalePosition": 1,
      "generateUtilityClass": true,
      "applicableComponents": ["layout", "wrapper", "max-width"],
      "containerQueryAware": true
    },
    {
      "name": "md",
      "value": "28rem",
      "category": "container",
      "namespace": "container",
      "semanticMeaning": "Medium container (448px)",
      "scalePosition": 2,
      "generateUtilityClass": true,
      "applicableComponents": ["layout", "wrapper", "max-width"],
      "containerQueryAware": true
    },
    {
      "name": "lg",
      "value": "32rem",
      "category": "container",
      "namespace": "container",
      "semanticMeaning": "Large container (512px)",
      "scalePosition": 3,
      "generateUtilityClass": true,
      "applicableComponents": ["layout", "wrapper", "max-width"],
      "containerQueryAware": true
    },
    {
      "name": "xl",
      "value": "36rem",
      "category": "container",
      "namespace": "container",
      "semanticMeaning": "Extra large container (576px)",
      "scalePosition": 4,
      "generateUtilityClass": true,
      "applicableComponents": ["layout", "wrapper", "max-width"],
      "containerQueryAware": true
    },
    {
      "name": "2xl",
      "value": "42rem",
      "category": "container",
      "namespace": "container",
      "semanticMeaning": "2XL container (672px)",
      "scalePosition": 5,
      "generateUtilityClass": true,
      "applicableComponents": ["layout", "wrapper", "max-width"],
      "containerQueryAware": true
    },
    {
      "name": "3xl",
      "value": "48rem",
      "category": "container",
      "namespace": "container",
      "semanticMeaning": "3XL container (768px)",
      "scalePosition": 6,
      "generateUtilityClass": true,
      "applicableComponents": ["layout", "wrapper", "max-width"],
      "containerQueryAware": true
    },
    {
      "name": "4xl",
      "value": "56rem",
      "category": "container",
      "namespace": "container",
      "semanticMeaning": "4XL container (896px)",
      "scalePosition": 7,
      "generateUtilityClass": true,
      "applicableComponents": ["layout", "wrapper", "max-width"],
      "containerQueryAware": true
    },
    {
      "name": "5xl",
      "value": "64rem",
      "category": "container",
      "namespace": "container",
      "semanticMeaning": "5XL container (1024px)",
      "scalePosition": 8,
      "generateUtilityClass": true,
      "applicableComponents": ["layout", "wrapper", "max-width"],
      "containerQueryAware": true
    },
    {
      "name": "6xl",
      "value": "72rem",
      "category": "container",
      "namespace": "container",
      "semanticMeaning": "6XL container (1152px)",
      "scalePosition": 9,
      "generateUtilityClass": true,
      "applicableComponents": ["layout", "wrapper", "max-width"],
      "containerQueryAware": true
    },
    {
      "name": "7xl",
      "value": "80rem",
      "category": "container",
      "namespace": "container",
      "semanticMeaning": "7XL container (1280px)",
      "scalePosition": 10,
      "generateUtilityClass": true,
      "applicableComponents": ["layout", "wrapper", "max-width"],
      "containerQueryAware": true
    },
    {
      "name": "8xl",
      "value": "90rem",
      "category": "container",
      "namespace": "container",
      "semanticMeaning": "8XL container (1440px)",
      "scalePosition": 11,
      "generateUtilityClass": true,
      "applicableComponents": ["layout", "wrapper", "max-width"],
      "containerQueryAware": true
    },
    {
      "name": "9xl",
      "value": "100rem",
      "category": "container",
      "namespace": "container",
      "semanticMeaning": "9XL container (1600px)",
      "scalePosition": 12,
      "generateUtilityClass": true,
      "applicableComponents": ["layout", "wrapper", "max-width"],
      "containerQueryAware": true
    },
    {
      "name": "square",
      "value": "1 / 1",
      "category": "aspect-ratio",
      "namespace": "aspect",
      "semanticMeaning": "Square aspect ratio for avatars and icons",
      "scalePosition": 0,
      "generateUtilityClass": true,
      "applicableComponents": ["avatar", "icon", "logo"]
    },
    {
      "name": "video",
      "value": "16 / 9",
      "category": "aspect-ratio",
      "namespace": "aspect",
      "semanticMeaning": "Video aspect ratio for media content",
      "scalePosition": 1,
      "generateUtilityClass": true,
      "applicableComponents": ["video", "iframe", "embed"]
    },
    {
      "name": "photo",
      "value": "4 / 3",
      "category": "aspect-ratio",
      "namespace": "aspect",
      "semanticMeaning": "Photo aspect ratio for images",
      "scalePosition": 2,
      "generateUtilityClass": true,
      "applicableComponents": ["img", "figure"]
    },
    {
      "name": "golden",
      "value": "1.618 / 1",
      "category": "aspect-ratio",
      "namespace": "aspect",
      "semanticMeaning": "Golden ratio for aesthetic layouts",
      "scalePosition": 3,
      "generateUtilityClass": true,
      "applicableComponents": ["media"]
    },
    {
      "name": "portrait",
      "value": "3 / 4",
      "category": "aspect-ratio",
      "namespace": "aspect",
      "semanticMeaning": "Portrait orientation",
      "scalePosition": 4,
      "generateUtilityClass": true,
      "applicableComponents": ["media"]
    },
    {
      "name": "landscape",
      "value": "4 / 3",
      "category": "aspect-ratio",
      "namespace": "aspect",
      "semanticMeaning": "Landscape orientation",
      "scalePosition": 5,
      "generateUtilityClass": true,
      "applicableComponents": ["media"]
    },
    {
      "name": "ultrawide",
      "value": "21 / 9",
      "category": "aspect-ratio",
      "namespace": "aspect",
      "semanticMeaning": "Ultrawide aspect ratio",
      "scalePosition": 6,
      "generateUtilityClass": true,
      "applicableComponents": ["media"]
    },
    {
      "name": "auto-fit-sm",
      "value": "repeat(auto-fit, minmax(var(--container-xs), 1fr))",
      "category": "grid-template-columns",
      "namespace": "grid-cols",
      "semanticMeaning": "Auto-fit grid for small cards",
      "scalePosition": 0,
      "generateUtilityClass": true,
      "applicableComponents": ["grid", "layout", "card-grid", "dashboard"]
    },
    {
      "name": "auto-fit-md",
      "value": "repeat(auto-fit, minmax(var(--container-sm), 1fr))",
      "category": "grid-template-columns",
      "namespace": "grid-cols",
      "semanticMeaning": "Auto-fit grid for medium cards",
      "scalePosition": 1,
      "generateUtilityClass": true,
      "applicableComponents": ["grid", "layout", "card-grid", "dashboard"]
    },
    {
      "name": "auto-fit-lg",
      "value": "repeat(auto-fit, minmax(var(--container-md), 1fr))",
      "category": "grid-template-columns",
      "namespace": "grid-cols",
      "semanticMeaning": "Auto-fit grid for large cards",
      "scalePosition": 2,
      "generateUtilityClass": true,
      "applicableComponents": ["grid", "layout", "card-grid", "dashboard"]
    },
    {
      "name": "auto-fill-sm",
      "value": "repeat(auto-fill, minmax(var(--container-xs), 1fr))",
      "category": "grid-template-columns",
      "namespace": "grid-cols",
      "semanticMeaning": "Auto-fill grid for small items",
      "scalePosition": 3,
      "generateUtilityClass": true,
      "applicableComponents": ["grid", "layout", "card-grid", "dashboard"]
    },
    {
      "name": "auto-fill-md",
      "value": "repeat(auto-fill, minmax(var(--container-sm), 1fr))",
      "category": "grid-template-columns",
      "namespace": "grid-cols",
      "semanticMeaning": "Auto-fill grid for medium items",
      "scalePosition": 4,
      "generateUtilityClass": true,
      "applicableComponents": ["grid", "layout", "card-grid", "dashboard"]
    },
    {
      "name": "auto-fill-lg",
      "value": "repeat(auto-fill, minmax(var(--container-md), 1fr))",
      "category": "grid-template-columns",
      "namespace": "grid-cols",
      "semanticMeaning": "Auto-fill grid for large items",
      "scalePosition": 5,
      "generateUtilityClass": true,
      "applicableComponents": ["grid", "layout", "card-grid", "dashboard"]
    },
    {
      "name": "2-cols",
      "value": "repeat(2, 1fr)",
      "category": "grid-template-columns",
      "namespace": "grid-cols",
      "semanticMeaning": "Two equal columns",
      "scalePosition": 6,
      "generateUtilityClass": true,
      "applicableComponents": ["grid", "layout", "card-grid", "dashboard"]
    },
    {
      "name": "3-cols",
      "value": "repeat(3, 1fr)",
      "category": "grid-template-columns",
      "namespace": "grid-cols",
      "semanticMeaning": "Three equal columns",
      "scalePosition": 7,
      "generateUtilityClass": true,
      "applicableComponents": ["grid", "layout", "card-grid", "dashboard"]
    },
    {
      "name": "4-cols",
      "value": "repeat(4, 1fr)",
      "category": "grid-template-columns",
      "namespace": "grid-cols",
      "semanticMeaning": "Four equal columns",
      "scalePosition": 8,
      "generateUtilityClass": true,
      "applicableComponents": ["grid", "layout", "card-grid", "dashboard"]
    },
    {
      "name": "12-cols",
      "value": "repeat(12, 1fr)",
      "category": "grid-template-columns",
      "namespace": "grid-cols",
      "semanticMeaning": "Twelve column layout system",
      "scalePosition": 9,
      "generateUtilityClass": true,
      "applicableComponents": ["grid", "layout", "card-grid", "dashboard"]
    },
    {
      "name": "sidebar",
      "value": "250px 1fr",
      "category": "grid-template-columns",
      "namespace": "grid-cols",
      "semanticMeaning": "Sidebar with main content",
      "scalePosition": 10,
      "generateUtilityClass": true,
      "applicableComponents": ["grid", "layout", "card-grid", "dashboard"]
    },
    {
      "name": "main-sidebar",
      "value": "1fr 250px",
      "category": "grid-template-columns",
      "namespace": "grid-cols",
      "semanticMeaning": "Main content with sidebar",
      "scalePosition": 11,
      "generateUtilityClass": true,
      "applicableComponents": ["grid", "layout", "card-grid", "dashboard"]
    },
    {
      "name": "auto",
      "value": "auto",
      "category": "grid-template-rows",
      "namespace": "grid-rows",
      "semanticMeaning": "Auto-sizing rows",
      "scalePosition": 0,
      "generateUtilityClass": true,
      "applicableComponents": ["grid", "layout", "card-grid"]
    },
    {
      "name": "header-main-footer",
      "value": "auto 1fr auto",
      "category": "grid-template-rows",
      "namespace": "grid-rows",
      "semanticMeaning": "Header, main content, footer layout",
      "scalePosition": 1,
      "generateUtilityClass": true,
      "applicableComponents": ["grid", "layout", "card-grid"]
    },
    {
      "name": "equal-2",
      "value": "repeat(2, 1fr)",
      "category": "grid-template-rows",
      "namespace": "grid-rows",
      "semanticMeaning": "Two equal rows",
      "scalePosition": 2,
      "generateUtilityClass": true,
      "applicableComponents": ["grid", "layout", "card-grid"]
    },
    {
      "name": "equal-3",
      "value": "repeat(3, 1fr)",
      "category": "grid-template-rows",
      "namespace": "grid-rows",
      "semanticMeaning": "Three equal rows",
      "scalePosition": 3,
      "generateUtilityClass": true,
      "applicableComponents": ["grid", "layout", "card-grid"]
    },
    {
      "name": "masonry",
      "value": "masonry",
      "category": "grid-template-rows",
      "namespace": "grid-rows",
      "semanticMeaning": "Masonry layout rows",
      "scalePosition": 4,
      "generateUtilityClass": true,
      "applicableComponents": ["grid", "layout", "card-grid"]
    },
    {
      "name": "hover",
      "value": "1.02",
      "category": "scale",
      "namespace": "scale",
      "semanticMeaning": "Subtle hover scale for interactive elements",
      "scalePosition": 0,
      "cognitiveLoad": 2,
      "generateUtilityClass": true,
      "applicableComponents": ["button", "card", "interactive"],
      "interactionType": "hover"
    },
    {
      "name": "active",
      "value": "0.98",
      "category": "scale",
      "namespace": "scale",
      "semanticMeaning": "Active/pressed scale for buttons",
      "scalePosition": 1,
      "cognitiveLoad": 1,
      "generateUtilityClass": true,
      "applicableComponents": ["button", "card", "interactive"],
      "interactionType": "active"
    },
    {
      "name": "focus",
      "value": "1.05",
      "category": "scale",
      "namespace": "scale",
      "semanticMeaning": "Focus scale for accessibility",
      "scalePosition": 2,
      "cognitiveLoad": 3,
      "generateUtilityClass": true,
      "applicableComponents": ["button", "card", "interactive"],
      "interactionType": "focus"
    },
    {
      "name": "disabled",
      "value": "0.95",
      "category": "scale",
      "namespace": "scale",
      "semanticMeaning": "Disabled state scale",
      "scalePosition": 3,
      "cognitiveLoad": 1,
      "generateUtilityClass": true,
      "applicableComponents": ["button", "card", "interactive"],
      "interactionType": "disabled"
    },
    {
      "name": "emphasis",
      "value": "1.1",
      "category": "scale",
      "namespace": "scale",
      "semanticMeaning": "Emphasis scale for important elements",
      "scalePosition": 4,
      "cognitiveLoad": 4,
      "generateUtilityClass": true,
      "applicableComponents": ["button", "card", "interactive"]
    },
    {
      "name": "dramatic",
      "value": "1.25",
      "category": "scale",
      "namespace": "scale",
      "semanticMeaning": "Dramatic scale for animations",
      "scalePosition": 5,
      "cognitiveLoad": 7,
      "generateUtilityClass": true,
      "applicableComponents": ["button", "card", "interactive"]
    },
    {
      "name": "center",
      "value": "-50%",
      "category": "translate",
      "namespace": "translate",
      "semanticMeaning": "Center positioning transform",
      "scalePosition": 0,
      "generateUtilityClass": true,
      "applicableComponents": ["modal", "dialog", "tooltip", "animations"]
    },
    {
      "name": "center-x",
      "value": "-50%, 0",
      "category": "translate",
      "namespace": "translate",
      "semanticMeaning": "Center horizontally",
      "scalePosition": 1,
      "generateUtilityClass": true,
      "applicableComponents": ["modal", "dialog", "tooltip", "animations"]
    },
    {
      "name": "center-y",
      "value": "0, -50%",
      "category": "translate",
      "namespace": "translate",
      "semanticMeaning": "Center vertically",
      "scalePosition": 2,
      "generateUtilityClass": true,
      "applicableComponents": ["modal", "dialog", "tooltip", "animations"]
    },
    {
      "name": "slide-up",
      "value": "0, -100%",
      "category": "translate",
      "namespace": "translate",
      "semanticMeaning": "Slide up animation",
      "scalePosition": 3,
      "generateUtilityClass": true,
      "applicableComponents": ["modal", "dialog", "tooltip", "animations"]
    },
    {
      "name": "slide-down",
      "value": "0, 100%",
      "category": "translate",
      "namespace": "translate",
      "semanticMeaning": "Slide down animation",
      "scalePosition": 4,
      "generateUtilityClass": true,
      "applicableComponents": ["modal", "dialog", "tooltip", "animations"]
    },
    {
      "name": "slide-left",
      "value": "-100%, 0",
      "category": "translate",
      "namespace": "translate",
      "semanticMeaning": "Slide left animation",
      "scalePosition": 5,
      "generateUtilityClass": true,
      "applicableComponents": ["modal", "dialog", "tooltip", "animations"]
    },
    {
      "name": "slide-right",
      "value": "100%, 0",
      "category": "translate",
      "namespace": "translate",
      "semanticMeaning": "Slide right animation",
      "scalePosition": 6,
      "generateUtilityClass": true,
      "applicableComponents": ["modal", "dialog", "tooltip", "animations"]
    },
    {
      "name": "flip",
      "value": "180deg",
      "category": "rotate",
      "namespace": "rotate",
      "semanticMeaning": "Flip rotation for icons and arrows",
      "scalePosition": 0,
      "generateUtilityClass": true,
      "applicableComponents": ["icon", "arrow", "dropdown"]
    },
    {
      "name": "quarter",
      "value": "90deg",
      "category": "rotate",
      "namespace": "rotate",
      "semanticMeaning": "Quarter turn rotation",
      "scalePosition": 1,
      "generateUtilityClass": true,
      "applicableComponents": ["icon", "arrow", "dropdown"]
    },
    {
      "name": "half",
      "value": "180deg",
      "category": "rotate",
      "namespace": "rotate",
      "semanticMeaning": "Half turn rotation",
      "scalePosition": 2,
      "generateUtilityClass": true,
      "applicableComponents": ["icon", "arrow", "dropdown"]
    },
    {
      "name": "three-quarter",
      "value": "270deg",
      "category": "rotate",
      "namespace": "rotate",
      "semanticMeaning": "Three quarter turn rotation",
      "scalePosition": 3,
      "generateUtilityClass": true,
      "applicableComponents": ["icon", "arrow", "dropdown"]
    },
    {
      "name": "min",
      "value": "min-content",
      "category": "width",
      "namespace": "w",
      "semanticMeaning": "Minimum content width",
      "scalePosition": 0,
      "generateUtilityClass": true,
      "applicableComponents": ["layout"]
    },
    {
      "name": "max",
      "value": "max-content",
      "category": "width",
      "namespace": "w",
      "semanticMeaning": "Maximum content width",
      "scalePosition": 1,
      "generateUtilityClass": true,
      "applicableComponents": ["layout"]
    },
    {
      "name": "fit",
      "value": "fit-content",
      "category": "width",
      "namespace": "w",
      "semanticMeaning": "Fit content width",
      "scalePosition": 2,
      "generateUtilityClass": true,
      "applicableComponents": ["layout"]
    },
    {
      "name": "full",
      "value": "100%",
      "category": "width",
      "namespace": "w",
      "semanticMeaning": "Full width",
      "scalePosition": 3,
      "generateUtilityClass": true,
      "applicableComponents": ["layout"]
    },
    {
      "name": "screen",
      "value": "100vw",
      "category": "width",
      "namespace": "w",
      "semanticMeaning": "Full viewport width",
      "scalePosition": 4,
      "generateUtilityClass": true,
      "applicableComponents": ["layout"]
    },
    {
      "name": "prose",
      "value": "65ch",
      "category": "width",
      "namespace": "w",
      "semanticMeaning": "Optimal reading width",
      "scalePosition": 5,
      "generateUtilityClass": true,
      "applicableComponents": ["content", "article"]
    },
    {
      "name": "dialog-sm",
      "value": "320px",
      "category": "width",
      "namespace": "w",
      "semanticMeaning": "Small dialog width",
      "scalePosition": 6,
      "generateUtilityClass": true,
      "applicableComponents": ["dialog", "modal"]
    },
    {
      "name": "dialog-md",
      "value": "480px",
      "category": "width",
      "namespace": "w",
      "semanticMeaning": "Medium dialog width",
      "scalePosition": 7,
      "generateUtilityClass": true,
      "applicableComponents": ["dialog", "modal"]
    },
    {
      "name": "dialog-lg",
      "value": "640px",
      "category": "width",
      "namespace": "w",
      "semanticMeaning": "Large dialog width",
      "scalePosition": 8,
      "generateUtilityClass": true,
      "applicableComponents": ["dialog", "modal"]
    },
    {
      "name": "dialog-xl",
      "value": "800px",
      "category": "width",
      "namespace": "w",
      "semanticMeaning": "Extra large dialog width",
      "scalePosition": 9,
      "generateUtilityClass": true,
      "applicableComponents": ["dialog", "modal"]
    },
    {
      "name": "sidebar",
      "value": "280px",
      "category": "width",
      "namespace": "w",
      "semanticMeaning": "Standard sidebar width",
      "scalePosition": 10,
      "generateUtilityClass": true,
      "applicableComponents": ["sidebar", "navigation"]
    },
    {
      "name": "sidebar-sm",
      "value": "240px",
      "category": "width",
      "namespace": "w",
      "semanticMeaning": "Compact sidebar width",
      "scalePosition": 11,
      "generateUtilityClass": true,
      "applicableComponents": ["sidebar", "navigation"]
    },
    {
      "name": "sidebar-lg",
      "value": "320px",
      "category": "width",
      "namespace": "w",
      "semanticMeaning": "Wide sidebar width",
      "scalePosition": 12,
      "generateUtilityClass": true,
      "applicableComponents": ["sidebar", "navigation"]
    },
    {
      "name": "none",
      "value": "0",
      "category": "backdrop-blur",
      "namespace": "backdrop-blur",
      "semanticMeaning": "No backdrop blur",
      "scalePosition": 0,
      "mathRelationship": "No blur",
      "generateUtilityClass": true,
      "applicableComponents": ["modal", "dialog", "overlay", "backdrop"]
    },
    {
      "name": "sm",
      "value": "4px",
      "category": "backdrop-blur",
      "namespace": "backdrop-blur",
      "semanticMeaning": "Small backdrop blur for overlays",
      "scalePosition": 1,
      "mathRelationship": "blur(4px)",
      "generateUtilityClass": true,
      "applicableComponents": ["modal", "dialog", "overlay", "backdrop"]
    },
    {
      "name": "DEFAULT",
      "value": "8px",
      "category": "backdrop-blur",
      "namespace": "backdrop-blur",
      "semanticMeaning": "Default backdrop blur for modals",
      "scalePosition": 2,
      "mathRelationship": "blur(8px)",
      "generateUtilityClass": true,
      "applicableComponents": ["modal", "dialog", "overlay", "backdrop"]
    },
    {
      "name": "md",
      "value": "12px",
      "category": "backdrop-blur",
      "namespace": "backdrop-blur",
      "semanticMeaning": "Medium backdrop blur for focus",
      "scalePosition": 3,
      "mathRelationship": "blur(12px)",
      "generateUtilityClass": true,
      "applicableComponents": ["modal", "dialog", "overlay", "backdrop"]
    },
    {
      "name": "lg",
      "value": "16px",
      "category": "backdrop-blur",
      "namespace": "backdrop-blur",
      "semanticMeaning": "Large backdrop blur for separation",
      "scalePosition": 4,
      "mathRelationship": "blur(16px)",
      "generateUtilityClass": true,
      "applicableComponents": ["modal", "dialog", "overlay", "backdrop"]
    },
    {
      "name": "xl",
      "value": "24px",
      "category": "backdrop-blur",
      "namespace": "backdrop-blur",
      "semanticMeaning": "Extra large blur for drama",
      "scalePosition": 5,
      "mathRelationship": "blur(24px)",
      "generateUtilityClass": true,
      "applicableComponents": ["modal", "dialog", "overlay", "backdrop"]
    },
    {
      "name": "2xl",
      "value": "40px",
      "category": "backdrop-blur",
      "namespace": "backdrop-blur",
      "semanticMeaning": "Maximum blur for strong effects",
      "scalePosition": 6,
      "mathRelationship": "blur(40px)",
      "generateUtilityClass": true,
      "applicableComponents": ["modal", "dialog", "overlay", "backdrop"]
    },
    {
      "name": "3xl",
      "value": "64px",
      "category": "backdrop-blur",
      "namespace": "backdrop-blur",
      "semanticMeaning": "Ultra blur for artistic effects",
      "scalePosition": 7,
      "mathRelationship": "blur(64px)",
      "generateUtilityClass": true,
      "applicableComponents": ["modal", "dialog", "overlay", "backdrop"]
    },
    {
      "name": "0",
      "value": "0px",
      "category": "border-width",
      "namespace": "border",
      "semanticMeaning": "No border",
      "scalePosition": 0,
      "mathRelationship": "No border",
      "generateUtilityClass": true,
      "applicableComponents": ["input", "card", "button"],
      "trustLevel": "low"
    },
    {
      "name": "DEFAULT",
      "value": "1px",
      "category": "border-width",
      "namespace": "border",
      "semanticMeaning": "Default border width",
      "scalePosition": 1,
      "mathRelationship": "1px (1x pixel)",
      "generateUtilityClass": true,
      "applicableComponents": ["input", "card", "button"],
      "trustLevel": "low"
    },
    {
      "name": "2",
      "value": "2px",
      "category": "border-width",
      "namespace": "border",
      "semanticMeaning": "Medium border for emphasis",
      "scalePosition": 2,
      "mathRelationship": "2px (2x pixel)",
      "generateUtilityClass": true,
      "applicableComponents": ["input", "card", "button"],
      "trustLevel": "low"
    },
    {
      "name": "4",
      "value": "4px",
      "category": "border-width",
      "namespace": "border",
      "semanticMeaning": "Thick border for strong emphasis",
      "scalePosition": 3,
      "mathRelationship": "4px (4x pixel)",
      "generateUtilityClass": true,
      "applicableComponents": ["decorative", "emphasis"],
      "trustLevel": "medium"
    },
    {
      "name": "8",
      "value": "8px",
      "category": "border-width",
      "namespace": "border",
      "semanticMeaning": "Extra thick decorative border",
      "scalePosition": 4,
      "mathRelationship": "8px (8x pixel)",
      "generateUtilityClass": true,
      "applicableComponents": ["decorative", "emphasis"],
      "trustLevel": "medium"
    }
  ],
  "accessibilityTarget": "AAA",
  "section508Compliant": true,
  "cognitiveLoadBudget": 15,
  "primaryColorSpace": "oklch",
  "generateDarkTheme": true,
  "enforceContrast": true,
  "enforceMotionSafety": true,
  "spacingSystem": "linear",
  "spacingMultiplier": 1.25,
  "spacingBaseUnit": 4,
  "generatedAt": "2025-08-28T19:21:05.024Z",
  "tokenCount": 225,
  "categoryCount": 26
}
